setup.py
core/__init__.py
core/base/__init__.py
core/base/corebaseclass.py
core/base/corebaseclassfactory.py
core/base/corebasefunctionwrapper.py
core/base/corebaseparameterholder.py
core/base/corebasesender.py
core/base/corecallback.py
core/context/__init__.py
core/context/corecontext.py
core/filesystem/__init__.py
core/filesystem/corefilesystem.py
core/logger/__init__.py
core/logger/corelogger.py
core/logger/coreloggerdebug.py
core/logger/coreloggerfile.py
core/logger/coreloggergtk.py
core/logger/coreloggermongo.py
core/logger/base/__init__.py
core/logger/base/corebaselogger.py
core/notification/__init__.py
core/notification/corelistener.py
core/notification/corenotification.py
core/notification/corenotificationcontainer.py
core/python/__init__.py
core/python/coreconfigparser.py
core/python/coredaemon.py
core/service/__init__.py
core/service/coreservice.py
core/service/coreservicecontainer.py
core/utils/__init__.py
core/utils/coreutils.py
core/utils/log.py
gotocorepy.egg-info/PKG-INFO
gotocorepy.egg-info/SOURCES.txt
gotocorepy.egg-info/dependency_links.txt
gotocorepy.egg-info/not-zip-safe
gotocorepy.egg-info/requires.txt
gotocorepy.egg-info/top_level.txt