Metadata-Version: 1.0
Name: gotocorepy
Version: 0.0.6
Summary: mvc framework, for python
Home-page: https://github.com/varadig/GotoCorePy
Author: Gabor Varadi
Author-email: varadi83gabor@gmail.com 
License: MIT
Platform: UNKNOWN
